awesome_panel_extensions/__init__.py
awesome_panel_extensions/bokeh.ext.json
awesome_panel_extensions/index.ts
awesome_panel_extensions/package-lock.json
awesome_panel_extensions/package.json
awesome_panel_extensions/tsconfig.json
awesome_panel_extensions/web_component.py
awesome_panel_extensions/_shared/__init__.py
awesome_panel_extensions/_shared/logger.py
awesome_panel_extensions/alpha/__init__.py
awesome_panel_extensions/assets/__init__.py
awesome_panel_extensions/assets/svg_icons.py
awesome_panel_extensions/awesome_panel/__init__.py
awesome_panel_extensions/awesome_panel/notebook.py
awesome_panel_extensions/awesome_panel/template.py
awesome_panel_extensions/bokeh_extensions/__init__.py
awesome_panel_extensions/bokeh_extensions/icon.py
awesome_panel_extensions/bokeh_extensions/icon.ts
awesome_panel_extensions/bokeh_extensions/index.ts
awesome_panel_extensions/bokeh_extensions/pivot_table.py
awesome_panel_extensions/bokeh_extensions/pivot_table.ts
awesome_panel_extensions/bokeh_extensions/shared.ts
awesome_panel_extensions/bokeh_extensions/web_component.py
awesome_panel_extensions/bokeh_extensions/web_component.ts
awesome_panel_extensions/bokeh_extensions/fast/__init__.py
awesome_panel_extensions/bokeh_extensions/fast/fast_anchor.py
awesome_panel_extensions/bokeh_extensions/fast/fast_button.py
awesome_panel_extensions/bokeh_extensions/fast/fast_checkbox_group.py
awesome_panel_extensions/bokeh_extensions/fast/fast_switch_group.py
awesome_panel_extensions/bokeh_extensions/fast/fast_text_input.py
awesome_panel_extensions/bokeh_extensions/fast/fast_textarea_input.py
awesome_panel_extensions/developer_tools/__init__.py
awesome_panel_extensions/developer_tools/designer/__init__.py
awesome_panel_extensions/developer_tools/designer/config.py
awesome_panel_extensions/developer_tools/designer/designer.html
awesome_panel_extensions/developer_tools/designer/designer.py
awesome_panel_extensions/developer_tools/designer/designer_core.py
awesome_panel_extensions-20221019.2.dist-info/LICENSE
awesome_panel_extensions-20221019.2.dist-info/METADATA
awesome_panel_extensions-20221019.2.dist-info/WHEEL
awesome_panel_extensions-20221019.2.dist-info/top_level.txt
awesome_panel_extensions-20221019.2.dist-info/RECORD
