Metadata-Version: 2.1
Name: awesome-panel-extensions
Version: 20221019.2
Summary: A package of awesome Panel extensions. Provided by awesome-panel.org
Author: awesome-panel
License: MIT License        
Project-URL: repository, https://github.com/awesome-panel/awesome-panel-extensions
Keywords: python,holoviz,panel,dataviz,dataapp,dashboard,datascience,analytics
Classifier: License :: OSI Approved :: MIT License
Classifier: Development Status :: 3 - Alpha
Classifier: Programming Language :: Python :: 3
Classifier: Programming Language :: Python :: 3.7
Classifier: Programming Language :: Python :: 3.8
Classifier: Programming Language :: Python :: 3.9
Classifier: Programming Language :: Python :: 3.10
Classifier: Operating System :: OS Independent
Classifier: Intended Audience :: Developers
Classifier: Intended Audience :: Education
Classifier: Intended Audience :: Financial and Insurance Industry
Classifier: Intended Audience :: Healthcare Industry
Classifier: Intended Audience :: Information Technology
Classifier: Intended Audience :: Legal Industry
Classifier: Intended Audience :: Other Audience
Classifier: Intended Audience :: Science/Research
Classifier: Natural Language :: English
Classifier: Topic :: Office/Business :: Financial
Classifier: Topic :: Office/Business
Classifier: Topic :: Scientific/Engineering :: Information Analysis
Classifier: Topic :: Scientific/Engineering :: Visualization
Classifier: Topic :: Scientific/Engineering
Classifier: Topic :: Software Development :: Libraries
Requires-Python: >=3.7
License-File: LICENSE
Requires-Dist: hvplot
Requires-Dist: pandas
Requires-Dist: panel (<1.0.0)
Requires-Dist: bokeh (<3.0.0)
Requires-Dist: lxml
Provides-Extra: dev
Requires-Dist: awesome-panel-cli[dev] ; extra == 'dev'
Requires-Dist: types-PyYAML ; extra == 'dev'
Requires-Dist: types-Markdown ; extra == 'dev'
Provides-Extra: examples
Requires-Dist: altair ; extra == 'examples'
Requires-Dist: awesome-panel-cli ; extra == 'examples'
Requires-Dist: holoviews ; extra == 'examples'
Requires-Dist: hvplot ; extra == 'examples'
Requires-Dist: matplotlib ; extra == 'examples'
Requires-Dist: notebook ; extra == 'examples'
Requires-Dist: pandas-profiling ; extra == 'examples'
Requires-Dist: pandas ; extra == 'examples'
Requires-Dist: plotly ; extra == 'examples'
Requires-Dist: seaborn ; extra == 'examples'
